outerop_instrumentation/__init__.py
outerop_instrumentation-0.1.2.dist-info/METADATA
outerop_instrumentation-0.1.2.dist-info/WHEEL
outerop_instrumentation-0.1.2.dist-info/RECORD
