Metadata-Version: 2.1
Name: outerop-instrumentation
Version: 0.1.2
Summary: 
Author: Alexander
Author-email: alex@outerop.com
Requires-Python: >=3.11,<4.0
Classifier: Programming Language :: Python :: 3
Classifier: Programming Language :: Python :: 3.11
Classifier: Programming Language :: Python :: 3.12
Requires-Dist: openai (>=1.14.2,<2.0.0)
Requires-Dist: opentelemetry-exporter-otlp (>=1.23.0,<2.0.0)
Requires-Dist: opentelemetry-instrumentation (>=0.44b0,<0.45)
Requires-Dist: opentelemetry-sdk (>=1.23.0,<2.0.0)
Requires-Dist: outerop (>=0.1.6,<0.2.0)
